akashi/__init__.py
akashi/__version__.py
akashi/akashi.py
akashi/config.py
akashi/core.py
akashi-1.0.0.dist-info/LICENSE
akashi-1.0.0.dist-info/METADATA
akashi-1.0.0.dist-info/WHEEL
akashi-1.0.0.dist-info/entry_points.txt
akashi-1.0.0.dist-info/top_level.txt
akashi-1.0.0.dist-info/RECORD
