Metadata-Version: 2.1
Name: akashi
Version: 1.0.0
Summary: Unofficial akashi command line tool.
Home-page: https://github.com/naoki-sawada/akashi-cli
Author: Naoki Sawada
Author-email: 
License: MIT
Platform: UNKNOWN
Classifier: License :: OSI Approved :: MIT License
Classifier: Programming Language :: Python
Classifier: Programming Language :: Python :: 3
Classifier: Programming Language :: Python :: 3.5
Classifier: Programming Language :: Python :: 3.6
Classifier: Programming Language :: Python :: Implementation :: CPython
Classifier: Programming Language :: Python :: Implementation :: PyPy
Requires-Python: >=3.5.0
Requires-Dist: click
Requires-Dist: keyring
Requires-Dist: selenium
